mobly/controllers/windows/__init__.py
mobly/controllers/windows/device_config.py
mobly/controllers/windows/windows_device.py
mobly/controllers/windows/lib/__init__.py
mobly/controllers/windows/lib/errors.py
mobly/controllers/windows/lib/ssh.py
mobly/controllers/windows/lib/win32_cim_info.py
mobly/controllers/windows/lib/windows_scheduled_task.py
mobly_windows-1.0.0.dist-info/LICENSE
mobly_windows-1.0.0.dist-info/METADATA
mobly_windows-1.0.0.dist-info/WHEEL
mobly_windows-1.0.0.dist-info/top_level.txt
mobly_windows-1.0.0.dist-info/RECORD
