Metadata-Version: 2.1
Name: mobly-windows
Version: 1.0.0
Summary: Mobly Windows controller module for using Python code to operate Windows devices in Mobly tests
Home-page: https://github.com/google/mobly-windows
Author: Google Inc.
Author-email: zhengshuyu@google.com
Maintainer-email: Shuyu Zheng <zhengshuyu@google.com>
License: 
Requires-Python: >=3.7
License-File: LICENSE
Requires-Dist: mobly >=1.12.2
Requires-Dist: dacite
Requires-Dist: paramiko
Requires-Dist: zmq
